jupyter_traitlets/__init__.py
jupyter_traitlets/_version.py
jupyter_traitlets/handlers.py
jupyter_traitlets/load_config.py
jupyter_traitlets/shim_config.py
jupyter_traitlets/conf/jupyter_my_ext_config.py
jupyter_traitlets/conf/jupyter_notebook_config.py
jupyter_traitlets/conf/jupyter_server_config.py
jupyter_traitlets/tests/__init__.py
jupyter_traitlets/tests/test_extensions.py
jupyter_traitlets/tests/test_handlers.py
jupyter_traitlets/tests/test_load_config.py
jupyter_traitlets/tests/test_shim_config.py
jupyter_traitlets/tests/fixtures_1/jupyter_notebook_config.py
jupyter_traitlets/tests/fixtures_1/jupyter_server_config.py
jupyter_traitlets/tests/fixtures_2/jupyter_my_ext_config.py
jupyter_traitlets/tests/fixtures_2/jupyter_notebook_config.py
jupyter_traitlets/tests/fixtures_2/jupyter_server_config.py
jupyter_traitlets-0.0.3.data/data/etc/jupyter/jupyter_notebook_config.d/jupyter_traitlets.json
jupyter_traitlets-0.0.3.data/data/etc/jupyter/jupyter_server_config.d/jupyter_traitlets.json
jupyter_traitlets-0.0.3.data/data/share/jupyter/labextensions/@datalayer/jupyter-traitlets/build_log.json
jupyter_traitlets-0.0.3.data/data/share/jupyter/labextensions/@datalayer/jupyter-traitlets/install.json
jupyter_traitlets-0.0.3.data/data/share/jupyter/labextensions/@datalayer/jupyter-traitlets/package.json
jupyter_traitlets-0.0.3.data/data/share/jupyter/labextensions/@datalayer/jupyter-traitlets/schemas/@datalayer/jupyter-traitlets/package.json.orig
jupyter_traitlets-0.0.3.data/data/share/jupyter/labextensions/@datalayer/jupyter-traitlets/schemas/@datalayer/jupyter-traitlets/plugin.json
jupyter_traitlets-0.0.3.data/data/share/jupyter/labextensions/@datalayer/jupyter-traitlets/static/icons_lib_index_js.5e50ff84ee56795b8851.js
jupyter_traitlets-0.0.3.data/data/share/jupyter/labextensions/@datalayer/jupyter-traitlets/static/icons_lib_index_js.5e50ff84ee56795b8851.js.map
jupyter_traitlets-0.0.3.dist-info/METADATA
jupyter_traitlets-0.0.3.dist-info/WHEEL
jupyter_traitlets-0.0.3.dist-info/licenses/LICENSE
jupyter_traitlets-0.0.3.dist-info/RECORD
